statopt/__init__.py
statopt/bucket.py
statopt/qhm.py
statopt/salsa.py
statopt/sasa.py
statopt/slope.py
statopt/ssls.py
statopt-0.2.dist-info/LICENSE
statopt-0.2.dist-info/METADATA
statopt-0.2.dist-info/WHEEL
statopt-0.2.dist-info/top_level.txt
statopt-0.2.dist-info/RECORD
