Metadata-Version: 2.1
Name: statopt
Version: 0.2
Summary: Statistical adaptive stochastic optimization methods
Home-page: https://github.com/microsoft/statopt
License: MIT
Platform: UNKNOWN
Requires-Dist: numpy
Requires-Dist: scipy
Requires-Dist: torch
